lab10/ex_counter_onoff/design_src/counter_onoff.v
module counter_onoff (
    input clk,
    input rst_n,
    input sw, // switch state signal
    output reg [5:0] cnt // counter value
);

localparam OFF = 0, ON = 1; // OFF for holding, ON for running

reg       S, S_nxt;
reg [5:0] cnt_nxt;

always @(*) begin
    case (S)
    OFF: begin
        cnt_nxt = cnt;
        S_nxt = sw ? ON : OFF;
    end
    ON: begin
        cnt_nxt = cnt + 1;
        S_nxt = sw ? OFF : ON;
    end
    default: begin
        cnt_nxt = cnt;
        S_nxt = S;
    end
    endcase
end

always @(posedge clk, negedge rst_n) begin
    if (~rst_n) begin
        S <= OFF;
        cnt <= 0;
    end
    else begin
        S <= S_nxt;
        cnt <= cnt_nxt;
    end
end
    
endmodule

lab10/ex_counter_onoff/wave.vcd
$version Generated by VerilatedVcd $end
$timescale 1ps $end
 $scope module TOP $end
  $var wire 1 # clk $end
  $var wire 1 $ rst_n $end
  $var wire 1 % sw $end
  $var wire 6 & cnt [5:0] $end
  $scope module counter_onoff $end
   $var wire 1 # clk $end
   $var wire 1 $ rst_n $end
   $var wire 1 % sw $end
   $var wire 6 & cnt [5:0] $end
   $var wire 32 * OFF [31:0] $end
   $var wire 32 + ON [31:0] $end
   $var wire 1 ' S $end
   $var wire 1 ( S_nxt $end
   $var wire 6 ) cnt_nxt [5:0] $end
  $upscope $end
 $upscope $end
$enddefinitions $end


#5
0#
0$
0%
b000000 &
0'
0(
b000000 )
b00000000000000000000000000000000 *
b00000000000000000000000000000001 +
#10
#15
#20
1#
#25
0#
#30
1#
#35
0#
1$
#40
1#
#45
0#
#50
1#
#55
0#
#60
1#
#65
0#
#70
1#
#75
0#
#80
1#
#85
0#
#90
1#
#95
0#
#100
1#
#105
0#
#110
1#
#115
0#
#120
1#
#125
0#
#130
1#
#135
0#
#140
1#
#145
0#
1%
1(
#150
1#
1'
0(
b000001 )
#155
0#
0%
1(
#160
1#
b000001 &
b000010 )
#165
0#
#170
1#
b000010 &
b000011 )
#175
0#
#180
1#
b000011 &
b000100 )
#185
0#
#190
1#
b000100 &
b000101 )
#195
0#
#200
1#
b000101 &
b000110 )
#205
0#
#210
1#
b000110 &
b000111 )
#215
0#
#220
1#
b000111 &
b001000 )
#225
0#
#230
1#
b001000 &
b001001 )
#235
0#
#240
1#
b001001 &
b001010 )
#245
0#
1%
0(
#250
1#
b001010 &
0'
1(
#255
0#
0%
0(
#260
1#
#265
0#
#270
1#
#275
0#
#280
1#
#285
0#
#290
1#
#295
0#
0$
b000000 &
b000000 )
#305
#315
#325
#335
#340
#345
#350
#355
1#
#360
0#
#365
1#
#370
0#
1$
#375
1#
#380
0#
#385
1#
#390
0#
#395
1#
#400
0#
#405
1#
#410
0#
#415
1#
#420
0#
#425
1#
#430
0#
1%
1(
#435
1#
1'
0(
b000001 )
#440
0#
0%
1(
#445
1#
b000001 &
b000010 )
#450
0#
#455
1#
b000010 &
b000011 )
#460
0#
#465
1#
b000011 &
b000100 )
#470
0#
#475
1#
b000100 &
b000101 )
#480
0#
#485
1#
b000101 &
b000110 )
#490
0#
#495
1#
b000110 &
b000111 )
#500
0#
#505
1#
b000111 &
b001000 )
#510
0#
#515
1#
b001000 &
b001001 )
#520
0#
#525
1#
b001001 &
b001010 )
#530
0#
1%
0(
#535
1#
b001010 &
0'
1(
#540
0#
0%
0(
#545
1#
#550
0#
#555
1#
#560
0#
#565
1#
#570
0#
#575
1#
#580
0#
#585
1#
#590
0#
#595
1#
#600
0#
#605
1#
#610
0#
#615
1#
#620
0#
#625
1#
#630
0#
1%
1(
#635
1#
1'
0(
b001011 )
#640
0#
0%
1(
#645
1#
b001011 &
b001100 )
#650
0#
#655
1#
b001100 &
b001101 )
#660
0#
#665
1#
b001101 &
b001110 )
#670
0#
#675
1#
b001110 &
b001111 )
#680
0#
#685
1#
b001111 &
b010000 )
#690
0#
#695
1#
b010000 &
b010001 )
#700
0#
#705
1#
b010001 &
b010010 )
#710
0#
#715
1#
b010010 &
b010011 )
#720
0#
#725
1#
b010011 &
b010100 )
#730
0#
#735
1#
b010100 &
b010101 )
#740
0#
#745
1#
b010101 &
b010110 )
#750
0#
#755
1#
b010110 &
b010111 )
#760
0#
#765
1#
b010111 &
b011000 )
#770
0#
#775
1#
b011000 &
b011001 )
#780
0#
#785
1#
b011001 &
b011010 )
#790
0#
#795
1#
b011010 &
b011011 )
#800
0#
#805
1#
b011011 &
b011100 )
#810
0#
#815
1#
b011100 &
b011101 )
#820
0#
#825
1#
b011101 &
b011110 )
#830
0#
#835
1#
b011110 &
b011111 )
#840
0#
#845
1#
b011111 &
b100000 )
#850
0#
#855
1#
b100000 &
b100001 )
#860
0#
#865
1#
b100001 &
b100010 )
#870
0#
#875
1#
b100010 &
b100011 )
#880
0#
#885
1#
b100011 &
b100100 )
#890
0#
#895
1#
b100100 &
b100101 )
#900
0#
#905
1#
b100101 &
b100110 )
#910
0#
#915
1#
b100110 &
b100111 )
#920
0#
#925
1#
b100111 &
b101000 )
#930
0#
#935
1#
b101000 &
b101001 )
#940
0#
#945
1#
b101001 &
b101010 )
#950
0#
#955
1#
b101010 &
b101011 )
#960
0#
#965
1#
b101011 &
b101100 )
#970
0#
#975
1#
b101100 &
b101101 )
#980
0#
#985
1#
b101101 &
b101110 )
#990
0#
#995
1#
b101110 &
b101111 )
#1000
0#
#1005
1#
b101111 &
b110000 )
#1010
0#
#1015
1#
b110000 &
b110001 )
#1020
0#
0$
b000000 &
0'
0(
b000000 )
#1030
#1040
#1050
#1060
#1065
#1070
#1075
#1080
1#
#1085
0#
#1090
1#
#1095
0#
1$
#1100
1#
#1105
0#
#1110
1#
#1115
0#
#1120
1#
#1125
0#
1%
1(
#1130
1#
1'
0(
b000001 )
#1135
0#
0%
1(
#1140
1#
b000001 &
b000010 )
#1145
0#
1%
0(
#1150
1#
b000010 &
0'
1(
#1155
0#
0%
0(
#1160
1#
#1165
0#
#1170
1#
#1175
0#
1%
1(
#1180
1#
1'
0(
b000011 )
#1185
0#
0%
1(
#1190
1#
b000011 &
b000100 )
#1195
0#
#1200
1#
b000100 &
b000101 )
#1205
0#
#1210
1#
b000101 &
b000110 )
#1215
0#
#1220
1#
b000110 &
b000111 )
#1225
0#
#1230
1#
b000111 &
b001000 )
#1235
0#
#1240
1#
b001000 &
b001001 )
#1245
0#
#1250
1#
b001001 &
b001010 )
#1255
0#
#1260
1#
b001010 &
b001011 )
#1265
0#
#1270
1#
b001011 &
b001100 )
#1275
0#
#1280
1#
b001100 &
b001101 )
#1285
0#
#1290
1#
b001101 &
b001110 )
#1295
0#
#1300
1#
b001110 &
b001111 )
#1305
0#
#1310
1#
b001111 &
b010000 )
#1315
0#
#1320
1#
b010000 &
b010001 )
#1325
0#
#1330
1#
b010001 &
b010010 )
#1335
0#
#1340
1#
b010010 &
b010011 )
#1345
0#
#1350
1#
b010011 &
b010100 )
#1355
0#
#1360
1#
b010100 &
b010101 )
#1365
0#
#1370
1#
b010101 &
b010110 )
#1375
0#
#1380
1#
b010110 &
b010111 )
#1385
0#
#1390
1#
b010111 &
b011000 )
#1395
0#
#1400
1#
b011000 &
b011001 )
#1405
0#
#1410
1#
b011001 &
b011010 )
#1415
0#
#1420
1#
b011010 &
b011011 )
#1425
0#
#1430
1#
b011011 &
b011100 )
#1435
0#
#1440
1#
b011100 &
b011101 )
#1445
0#
#1450
1#
b011101 &
b011110 )
#1455
0#
#1460
1#
b011110 &
b011111 )
#1465
0#
#1470
1#
b011111 &
b100000 )
#1475
0#
#1480
1#
b100000 &
b100001 )
#1485
0#
#1490
1#
b100001 &
b100010 )
#1495
0#
#1500
1#
b100010 &
b100011 )
#1505
0#
#1510
1#
b100011 &
b100100 )
#1515
0#
#1520
1#
b100100 &
b100101 )
#1525
0#
#1530
1#
b100101 &
b100110 )
#1535
0#
#1540
1#
b100110 &
b100111 )
#1545
0#
#1550
1#
b100111 &
b101000 )
#1555
0#
#1560
1#
b101000 &
b101001 )
#1565
0#
#1570
1#
b101001 &
b101010 )
#1575
0#
#1580
1#
b101010 &
b101011 )
#1585
0#
#1590
1#
b101011 &
b101100 )
#1595
0#
#1600
1#
b101100 &
b101101 )
#1605
0#
#1610
1#
b101101 &
b101110 )
#1615
0#
#1620
1#
b101110 &
b101111 )
#1625
0#
#1630
1#
b101111 &
b110000 )
#1635
0#
#1640
1#
b110000 &
b110001 )
#1645
0#
#1650
1#
b110001 &
b110010 )
#1655
0#
#1660
1#
b110010 &
b110011 )
#1665
0#
#1670
1#
b110011 &
b110100 )
#1675
0#
#1680
1#
b110100 &
b110101 )
#1685
0#
#1690
1#
b110101 &
b110110 )
#1695
0#
#1700
1#
b110110 &
b110111 )
#1705
0#
#1710
1#
b110111 &
b111000 )
#1715
0#
#1720
1#
b111000 &
b111001 )
#1725
0#
#1730
1#
b111001 &
b111010 )
#1735
0#
#1740
1#
b111010 &
b111011 )
#1745
0#
#1750
1#
b111011 &
b111100 )
#1755
0#
#1760
1#
b111100 &
b111101 )
#1765
0#
#1770
1#
b111101 &
b111110 )
#1775
0#
#1780
1#
b111110 &
b111111 )
#1785
0#
#1790
1#
b111111 &
b000000 )
#1795
0#
#1800
1#
b000000 &
b000001 )
#1805
0#
#1810
1#
b000001 &
b000010 )
#1815
0#
#1820
1#
b000010 &
b000011 )
#1825
0#
#1830
1#
b000011 &
b000100 )
#1835
0#
#1840
1#
b000100 &
b000101 )
#1845
0#
#1850
1#
b000101 &
b000110 )
#1855
0#
#1860
1#
b000110 &
b000111 )
#1865
0#
#1870
1#
b000111 &
b001000 )
#1875
0#
#1880
1#
b001000 &
b001001 )
#1885
0#
#1890
1#
b001001 &
b001010 )
#1895
0#
#1900
1#
b001010 &
b001011 )
#1905
0#
#1910
1#
b001011 &
b001100 )
#1915
0#
#1920
1#
b001100 &
b001101 )
#1925
0#
#1930
1#
b001101 &
b001110 )
#1935
0#
#1940
1#
b001110 &
b001111 )
#1945
0#
#1950
1#
b001111 &
b010000 )
#1955
0#
#1960
1#
b010000 &
b010001 )
#1965
0#
#1970
1#
b010001 &
b010010 )
#1975
0#
#1980
1#
b010010 &
b010011 )
#1985
0#
#1990
1#
b010011 &
b010100 )
#1995
0#
#2000
1#
b010100 &
b010101 )
#2005
0#
#2010
1#
b010101 &
b010110 )
#2015
0#
#2020
1#
b010110 &
b010111 )
#2025
0#
#2030
1#
b010111 &
b011000 )
#2035
0#
#2040
1#
b011000 &
b011001 )
#2045
0#
#2050
1#
b011001 &
b011010 )
#2055
0#
#2060
1#
b011010 &
b011011 )
#2065
0#
#2070
1#
b011011 &
b011100 )
#2075
0#
#2080
1#
b011100 &
b011101 )
#2085
0#
#2090
1#
b011101 &
b011110 )
#2095
0#
#2100
1#
b011110 &
b011111 )
#2105
0#
#2110
1#
b011111 &
b100000 )
#2115
0#
#2120
1#
b100000 &
b100001 )
#2125
0#
#2130
1#
b100001 &
b100010 )
#2135
0#
#2140
1#
b100010 &
b100011 )
#2145
0#
#2150
1#
b100011 &
b100100 )
#2155
0#
#2160
1#
b100100 &
b100101 )
#2165
0#
#2170
1#
b100101 &
b100110 )
#2175
0#
#2180
1#
b100110 &
b100111 )
#2185
0#
#2190
1#
b100111 &
b101000 )
#2195
0#
#2200
1#
b101000 &
b101001 )
#2205
0#
#2210
1#
b101001 &
b101010 )
#2215
0#
#2220
1#
b101010 &
b101011 )
#2225
0#
#2230
1#
b101011 &
b101100 )
#2235
0#
#2240
1#
b101100 &
b101101 )
#2245
0#
#2250
1#
b101101 &
b101110 )
#2255
0#
#2260
1#
b101110 &
b101111 )
#2265
0#
#2270
1#
b101111 &
b110000 )
#2275
0#
#2280
1#
b110000 &
b110001 )
#2285
0#
0$
b000000 &
0'
0(
b000000 )
#2295
#2305
#2315
#2325
#2330
#2335
#2340
#2345
1#
#2350
0#
#2355
1#
#2360
0#
1$
#2365
1#
#2370
0#
#2375
1#
#2380
0#
#2385
1#
#2390
0#
#2395
1#
#2400
0#
#2405
1#
#2410
0#
#2415
1#
#2420
0#
#2425
1#
#2430
0#
#2435
1#
#2440
0#
#2445
1#
#2450
0#
#2455
1#
#2460
0#
#2465
1#
#2470
0#
1%
1(
#2475
1#
1'
0(
b000001 )
#2480
0#
0%
1(
#2485
1#
b000001 &
b000010 )
#2490
0#
#2495
1#
b000010 &
b000011 )
#2500
0#
#2505
1#
b000011 &
b000100 )
#2510
0#
#2515
1#
b000100 &
b000101 )
#2520
0#
#2525
1#
b000101 &
b000110 )
#2530
0#
#2535
1#
b000110 &
b000111 )
#2540
0#
#2545
1#
b000111 &
b001000 )
#2550
0#
#2555
1#
b001000 &
b001001 )
#2560
0#
#2565
1#
b001001 &
b001010 )
#2570
0#
#2575
1#
b001010 &
b001011 )
#2580
0#
#2585
1#
b001011 &
b001100 )
#2590
0#
#2595
1#
b001100 &
b001101 )
#2600
0#
#2605
1#
b001101 &
b001110 )
#2610
0#
#2615
1#
b001110 &
b001111 )
#2620
0#
#2625
1#
b001111 &
b010000 )
#2630
0#
#2635
1#
b010000 &
b010001 )
#2640
0#
#2645
1#
b010001 &
b010010 )
#2650
0#
#2655
1#
b010010 &
b010011 )
#2660
0#
#2665
1#
b010011 &
b010100 )
#2670
0#
1%
0(
#2675
1#
b010100 &
0'
1(
#2680
0#
0%
0(
#2685
1#
#2690
0#
#2695
1#
#2700
0#
#2705
1#
#2710
0#
#2715
1#
#2720
0#
#2725
1#
#2730
0#
#2735
1#
#2740
0#
#2745
1#
#2750
0#
#2755
1#
#2760
0#
#2765
1#
#2770
0#
#2775
1#
#2780
0#
#2785
1#
#2790
0#
#2795
1#
#2800
0#
#2805
1#
#2810
0#
#2815
1#
#2820
0#
#2825
1#
#2830
0#
#2835
1#
#2840
0#
#2845
1#
#2850
0#
#2855
1#
#2860
0#
#2865
1#
#2870
0#
1%
1(
#2875
1#
1'
0(
b010101 )
#2880
0#
0%
1(
#2885
1#
b010101 &
b010110 )
#2890
0#
#2895
1#
b010110 &
b010111 )
#2900
0#
#2905
1#
b010111 &
b011000 )
#2910
0#
#2915
1#
b011000 &
b011001 )
#2920
0#
#2925
1#
b011001 &
b011010 )
#2930
0#
#2935
1#
b011010 &
b011011 )
#2940
0#
#2945
1#
b011011 &
b011100 )
#2950
0#
#2955
1#
b011100 &
b011101 )
#2960
0#
#2965
1#
b011101 &
b011110 )
#2970
0#
#2975
1#
b011110 &
b011111 )
#2980
0#
#2985
1#
b011111 &
b100000 )
#2990
0#
#2995
1#
b100000 &
b100001 )
#3000
0#
#3005
1#
b100001 &
b100010 )
#3010
0#
#3015
1#
b100010 &
b100011 )
#3020
0#
#3025
1#
b100011 &
b100100 )
#3030
0#
#3035
1#
b100100 &
b100101 )
#3040
0#
#3045
1#
b100101 &
b100110 )
#3050
0#
#3055
1#
b100110 &
b100111 )
#3060
0#
#3065
1#
b100111 &
b101000 )
#3070
0#
#3075
1#
b101000 &
b101001 )
#3080
0#
#3085
1#
b101001 &
b101010 )
#3090
0#
#3095
1#
b101010 &
b101011 )
#3100
0#
#3105
1#
b101011 &
b101100 )
#3110
0#
#3115
1#
b101100 &
b101101 )
#3120
0#
#3125
1#
b101101 &
b101110 )
#3130
0#
#3135
1#
b101110 &
b101111 )
#3140
0#
#3145
1#
b101111 &
b110000 )
#3150
0#
#3155
1#
b110000 &
b110001 )
#3160
0#
#3165
1#
b110001 &
b110010 )
#3170
0#
#3175
1#
b110010 &
b110011 )
#3180
0#
#3185
1#
b110011 &
b110100 )
#3190
0#
#3195
1#
b110100 &
b110101 )
#3200
0#
#3205
1#
b110101 &
b110110 )
#3210
0#
#3215
1#
b110110 &
b110111 )
#3220
0#
#3225
1#
b110111 &
b111000 )
#3230
0#
#3235
1#
b111000 &
b111001 )
#3240
0#
#3245
1#
b111001 &
b111010 )
#3250
0#
#3255
1#
b111010 &
b111011 )
#3260
0#
#3265
1#
b111011 &
b111100 )
#3270
0#
#3275
1#
b111100 &
b111101 )
#3280
0#
#3285
1#
b111101 &
b111110 )
#3290
0#
#3295
1#
b111110 &
b111111 )
#3300
0#
#3305
1#
b111111 &
b000000 )
#3310
0#
#3315
1#
b000000 &
b000001 )
#3320
0#
#3325
1#
b000001 &
b000010 )
#3330
0#
#3335
1#
b000010 &
b000011 )
#3340
0#
#3345
1#
b000011 &
b000100 )
#3350
0#
#3355
1#
b000100 &
b000101 )
#3360
0#
#3365
1#
b000101 &
b000110 )
#3370
0#
#3375
1#
b000110 &
b000111 )
#3380
0#
#3385
1#
b000111 &
b001000 )
#3390
0#
#3395
1#
b001000 &
b001001 )
#3400
0#
#3405
1#
b001001 &
b001010 )
#3410
0#
#3415
1#
b001010 &
b001011 )
#3420
0#
#3425
1#
b001011 &
b001100 )
#3430
0#
#3435
1#
b001100 &
b001101 )
#3440
0#
#3445
1#
b001101 &
b001110 )
#3450
0#
#3455
1#
b001110 &
b001111 )
#3460
0#
#3465
1#
b001111 &
b010000 )
#3470
0#
#3475
1#
b010000 &
b010001 )
#3480
0#
#3485
1#
b010001 &
b010010 )
#3490
0#
#3495
1#
b010010 &
b010011 )
#3500
0#
#3505
1#
b010011 &
b010100 )
#3510
0#
#3515
1#
b010100 &
b010101 )
#3520
0#
#3525
1#
b010101 &
b010110 )
#3530
0#
#3535
1#
b010110 &
b010111 )
#3540
0#
#3545
1#
b010111 &
b011000 )
#3550
0#
#3555
1#
b011000 &
b011001 )
#3560
0#
#3565
1#
b011001 &
b011010 )
#3570
0#
#3575
1#
b011010 &
b011011 )
#3580
0#
#3585
1#
b011011 &
b011100 )
#3590
0#
#3595
1#
b011100 &
b011101 )
#3600
0#
#3605
1#
b011101 &
b011110 )
#3610
0#
#3615
1#
b011110 &
b011111 )
#3620
0#
#3625
1#
b011111 &
b100000 )
#3630
0#
#3635
1#
b100000 &
b100001 )
#3640
0#
#3645
1#
b100001 &
b100010 )
#3650
0#
#3655
1#
b100010 &
b100011 )
#3660
0#
#3665
1#
b100011 &
b100100 )
#3670
0#
#3675
1#
b100100 &
b100101 )
#3680
0#
#3685
1#
b100101 &
b100110 )
#3690
0#
#3695
1#
b100110 &
b100111 )
#3700
0#
#3705
1#
b100111 &
b101000 )
#3710
0#
#3715
1#
b101000 &
b101001 )
#3720
0#
#3725
1#
b101001 &
b101010 )
#3730
0#
#3735
1#
b101010 &
b101011 )
#3740
0#
#3745
1#
b101011 &
b101100 )
#3750
0#
#3755
1#
b101100 &
b101101 )
#3760
0#
#3765
1#
b101101 &
b101110 )
#3770
0#
#3775
1#
b101110 &
b101111 )
#3780
0#
#3785
1#
b101111 &
b110000 )
#3790
0#
#3795
1#
b110000 &
b110001 )
#3800
0#
#3805
1#
b110001 &
b110010 )
#3810
0#
#3815
1#
b110010 &
b110011 )
#3820
0#
#3825
1#
b110011 &
b110100 )
#3830
0#
#3835
1#
b110100 &
b110101 )
#3840
0#
#3845
1#
b110101 &
b110110 )
#3850
0#
#3855
1#
b110110 &
b110111 )
#3860
0#
#3865
1#
b110111 &
b111000 )
#3870
0#
#3875
1#
b111000 &
b111001 )
#3880
0#
#3885
1#
b111001 &
b111010 )
#3890
0#
#3895
1#
b111010 &
b111011 )
#3900
0#
#3905
1#
b111011 &
b111100 )
#3910
0#
#3915
1#
b111100 &
b111101 )
#3920
0#
#3925
1#
b111101 &
b111110 )
#3930
0#
#3935
1#
b111110 &
b111111 )
#3940
0#
#3945
1#
b111111 &
b000000 )
#3950
0#
#3955
1#
b000000 &
b000001 )
#3960
0#
#3965
1#
b000001 &
b000010 )
#3970
0#
#3975
1#
b000010 &
b000011 )
#3980
0#
#3985
1#
b000011 &
b000100 )
#3990
0#
#3995
1#
b000100 &
b000101 )
#4000
0#
#4005
1#
b000101 &
b000110 )
#4010
0#
#4015
1#
b000110 &
b000111 )
#4020
0#
#4025
1#
b000111 &
b001000 )
#4030
0#
#4035
1#
b001000 &
b001001 )
#4040
0#
#4045
1#
b001001 &
b001010 )
#4050
0#
#4055
1#
b001010 &
b001011 )
#4060
0#
#4065
1#
b001011 &
b001100 )
#4070
0#
#4075
1#
b001100 &
b001101 )
#4080
0#
#4085
1#
b001101 &
b001110 )
#4090
0#
#4095
1#
b001110 &
b001111 )
#4100
0#
#4105
1#
b001111 &
b010000 )
#4110
0#
#4115
1#
b010000 &
b010001 )
#4120
0#
#4125
1#
b010001 &
b010010 )
#4130
0#
#4135
1#
b010010 &
b010011 )
#4140
0#
#4145
1#
b010011 &
b010100 )
#4150
0#
#4155
1#
b010100 &
b010101 )
#4160
0#
#4165
1#
b010101 &
b010110 )
#4170
0#
#4175
1#
b010110 &
b010111 )
#4180
0#
#4185
1#
b010111 &
b011000 )
#4190
0#
#4195
1#
b011000 &
b011001 )
#4200
0#
#4205
1#
b011001 &
b011010 )
#4210
0#
#4215
1#
b011010 &
b011011 )
#4220
0#
#4225
1#
b011011 &
b011100 )
#4230
0#
#4235
1#
b011100 &
b011101 )
#4240
0#
#4245
1#
b011101 &
b011110 )
#4250
0#
#4255
1#
b011110 &
b011111 )
#4260
0#
#4265
1#
b011111 &
b100000 )
#4270
0#
#4275
1#
b100000 &
b100001 )
#4280
0#
#4285
1#
b100001 &
b100010 )
#4290
0#
#4295
1#
b100010 &
b100011 )
#4300
0#
#4305
1#
b100011 &
b100100 )
#4310
0#
#4315
1#
b100100 &
b100101 )
#4320
0#
#4325
1#
b100101 &
b100110 )
#4330
0#
#4335
1#
b100110 &
b100111 )
#4340
0#
#4345
1#
b100111 &
b101000 )
#4350
0#
#4355
1#
b101000 &
b101001 )
#4360
0#
#4365
1#
b101001 &
b101010 )
#4370
0#
#4375
1#
b101010 &
b101011 )
#4380
0#
#4385
1#
b101011 &
b101100 )
#4390
0#
#4395
1#
b101100 &
b101101 )
#4400
0#
#4405
1#
b101101 &
b101110 )
#4410
0#
#4415
1#
b101110 &
b101111 )
#4420
0#
#4425
1#
b101111 &
b110000 )
#4430
0#
#4435
1#
b110000 &
b110001 )
#4440
0#
#4445
1#
b110001 &
b110010 )
#4450
0#
#4455
1#
b110010 &
b110011 )
#4460
0#
#4465
1#
b110011 &
b110100 )
#4470
0#
#4475
1#
b110100 &
b110101 )
#4480
0#
#4485
1#
b110101 &
b110110 )
#4490
0#
#4495
1#
b110110 &
b110111 )
#4500
0#
#4505
1#
b110111 &
b111000 )
#4510
0#
#4515
1#
b111000 &
b111001 )
#4520
0#
#4525
1#
b111001 &
b111010 )
#4530
0#
#4535
1#
b111010 &
b111011 )
#4540
0#
#4545
1#
b111011 &
b111100 )
#4550
0#
#4555
1#
b111100 &
b111101 )
#4560
0#
#4565
1#
b111101 &
b111110 )
#4570
0#
#4575
1#
b111110 &
b111111 )
#4580
0#
#4585
1#
b111111 &
b000000 )
#4590
0#
#4595
1#
b000000 &
b000001 )
#4600
0#
#4605
1#
b000001 &
b000010 )
#4610
0#
#4615
1#
b000010 &
b000011 )
#4620
0#
#4625
1#
b000011 &
b000100 )
#4630
0#
#4635
1#
b000100 &
b000101 )
#4640
0#
#4645
1#
b000101 &
b000110 )
#4650
0#
#4655
1#
b000110 &
b000111 )
#4660
0#
#4665
1#
b000111 &
b001000 )
#4670
0#
#4675
1#
b001000 &
b001001 )
#4680
0#
#4685
1#
b001001 &
b001010 )
#4690
0#
#4695
1#
b001010 &
b001011 )
#4700
0#
#4705
1#
b001011 &
b001100 )
#4710
0#
#4715
1#
b001100 &
b001101 )
#4720
0#
#4725
1#
b001101 &
b001110 )
#4730
0#
#4735
1#
b001110 &
b001111 )
#4740
0#
#4745
1#
b001111 &
b010000 )
#4750
0#
#4755
1#
b010000 &
b010001 )
#4760
0#
#4765
1#
b010001 &
b010010 )
#4770
0#
#4775
1#
b010010 &
b010011 )
#4780
0#
#4785
1#
b010011 &
b010100 )
#4790
0#
#4795
1#
b010100 &
b010101 )
#4800
0#
#4805
1#
b010101 &
b010110 )
#4810
0#
#4815
1#
b010110 &
b010111 )
#4820
0#
#4825
1#
b010111 &
b011000 )
#4830
0#
#4835
1#
b011000 &
b011001 )
#4840
0#
#4845
1#
b011001 &
b011010 )
#4850
0#
#4855
1#
b011010 &
b011011 )
#4860
0#
#4865
1#
b011011 &
b011100 )
#4870
0#
#4875
1#
b011100 &
b011101 )
#4880
0#
#4885
1#
b011101 &
b011110 )
#4890
0#
#4895
1#
b011110 &
b011111 )
#4900
0#
#4905
1#
b011111 &
b100000 )
#4910
0#
#4915
1#
b100000 &
b100001 )
#4920
0#
#4925
1#
b100001 &
b100010 )
#4930
0#
#4935
1#
b100010 &
b100011 )
#4940
0#
#4945
1#
b100011 &
b100100 )
#4950
0#
#4955
1#
b100100 &
b100101 )
#4960
0#
#4965
1#
b100101 &
b100110 )
#4970
0#
#4975
1#
b100110 &
b100111 )
#4980
0#
#4985
1#
b100111 &
b101000 )
#4990
0#
#4995
1#
b101000 &
b101001 )
#5000
0#
#5005
1#
b101001 &
b101010 )
#5010
0#
#5015
1#
b101010 &
b101011 )
#5020
0#
#5025
1#
b101011 &
b101100 )
#5030
0#
#5035
1#
b101100 &
b101101 )
#5040
0#
#5045
1#
b101101 &
b101110 )
#5050
0#
#5055
1#
b101110 &
b101111 )
#5060
0#
#5065
1#
b101111 &
b110000 )
#5070
0#
#5075
1#
b110000 &
b110001 )
#5080
0#
#5085
1#
b110001 &
b110010 )
#5090
0#
#5095
1#
b110010 &
b110011 )
#5100
0#
#5105
1#
b110011 &
b110100 )
#5110
0#
#5115
1#
b110100 &
b110101 )
#5120
0#
#5125
1#
b110101 &
b110110 )
#5130
0#
#5135
1#
b110110 &
b110111 )
#5140
0#
#5145
1#
b110111 &
b111000 )
#5150
0#
#5155
1#
b111000 &
b111001 )
#5160
0#
#5165
1#
b111001 &
b111010 )
#5170
0#
#5175
1#
b111010 &
b111011 )
#5180
0#
#5185
1#
b111011 &
b111100 )
#5190
0#
#5195
1#
b111100 &
b111101 )
#5200
0#
#5205
1#
b111101 &
b111110 )
#5210
0#
#5215
1#
b111110 &
b111111 )
#5220
0#
#5225
1#
b111111 &
b000000 )
#5230
0#
#5235
1#
b000000 &
b000001 )
#5240
0#
#5245
1#
b000001 &
b000010 )
#5250
0#
0$
b000000 &
0'
0(
b000000 )
#5260
#5270
#5280
#5290
#5295
#5300
#5305
#5310
1#
#5315
0#
#5320
1#
#5325
0#
1$
#5330
1#
#5335
0#
#5340
1#
#5345
0#
#5350
1#
#5355
0#
#5360
1#
#5365
0#
#5370
1#
#5375
0#
#5380
1#
#5385
0#
#5390
1#
#5395
0#
#5400
1#
#5405
0#
#5410
1#
#5415
0#
1%
1(
#5420
1#
1'
0(
b000001 )
#5425
0#
0%
1(
#5430
1#
b000001 &
b000010 )
#5435
0#
#5440
1#
b000010 &
b000011 )
#5445
0#
1%
0(
#5450
1#
b000011 &
0'
1(
#5455
0#
0%
0(
#5460
1#
#5465
0#
#5470
1#
#5475
0#
1%
1(
#5480
1#
1'
0(
b000100 )
#5485
0#
0%
1(
#5490
1#
b000100 &
b000101 )
#5495
0#
#5500
1#
b000101 &
b000110 )
#5505
0#
#5510
1#
b000110 &
b000111 )
#5515
0#
1%
0(
#5520
1#
b000111 &
0'
1(
#5525
0#
0%
0(
#5530
1#
#5535
0#
#5540
1#
#5545
0#
#5550
1#
#5555
0#
1%
1(
#5560
1#
1'
0(
b001000 )
#5565
0#
0%
1(
#5570
1#
b001000 &
b001001 )
#5575
0#
#5580
1#
b001001 &
b001010 )
#5585
0#
#5590
1#
b001010 &
b001011 )
#5595
0#
#5600
1#
b001011 &
b001100 )
#5605
0#
#5610
1#
b001100 &
b001101 )
#5615
0#
#5620
1#
b001101 &
b001110 )
#5625
0#
#5630
1#
b001110 &
b001111 )
#5635
0#
#5640
1#
b001111 &
b010000 )
#5645
0#
#5650
1#
b010000 &
b010001 )
#5655
0#
#5660
1#
b010001 &
b010010 )
#5665
0#
#5670
1#
b010010 &
b010011 )
#5675
0#
#5680
1#
b010011 &
b010100 )
#5685
0#
#5690
1#
b010100 &
b010101 )
#5695
0#
#5700
1#
b010101 &
b010110 )
#5705
0#
#5710
1#
b010110 &
b010111 )
#5715
0#
#5720
1#
b010111 &
b011000 )
#5725
0#
#5730
1#
b011000 &
b011001 )
#5735
0#
#5740
1#
b011001 &
b011010 )
#5745
0#
#5750
1#
b011010 &
b011011 )
#5755
0#
#5760
1#
b011011 &
b011100 )
#5765
0#
#5770
1#
b011100 &
b011101 )
#5775
0#
#5780
1#
b011101 &
b011110 )
#5785
0#
#5790
1#
b011110 &
b011111 )
#5795
0#
#5800
1#
b011111 &
b100000 )
#5805
0#
#5810
1#
b100000 &
b100001 )
#5815
0#
#5820
1#
b100001 &
b100010 )
#5825
0#
#5830
1#
b100010 &
b100011 )
#5835
0#
#5840
1#
b100011 &
b100100 )
#5845
0#
#5850
1#
b100100 &
b100101 )
#5855
0#
#5860
1#
b100101 &
b100110 )
#5865
0#
#5870
1#
b100110 &
b100111 )
#5875
0#
#5880
1#
b100111 &
b101000 )
#5885
0#
#5890
1#
b101000 &
b101001 )
#5895
0#
#5900
1#
b101001 &
b101010 )
#5905
0#
#5910
1#
b101010 &
b101011 )
#5915
0#
#5920
1#
b101011 &
b101100 )
#5925
0#
#5930
1#
b101100 &
b101101 )
#5935
0#
#5940
1#
b101101 &
b101110 )
#5945
0#
#5950
1#
b101110 &
b101111 )
#5955
0#
#5960
1#
b101111 &
b110000 )
#5965
0#
#5970
1#
b110000 &
b110001 )
#5975
0#
#5980
1#
b110001 &
b110010 )
#5985
0#
#5990
1#
b110010 &
b110011 )
#5995
0#
#6000
1#
b110011 &
b110100 )
#6005
0#
#6010
1#
b110100 &
b110101 )
#6015
0#
#6020
1#
b110101 &
b110110 )
#6025
0#
#6030
1#
b110110 &
b110111 )
#6035
0#
