lab04/pr_math/design_src/math.v
module math (
    input  [3:0] a,
    output reg [7:0] mul2, // output a*2
    output reg [3:0] div2, // output a/2
    output reg [3:0] mod2, // output a%2
    output reg [7:0] mul4, // output a*4
    output reg [3:0] div4, // output a/4
    output reg [3:0] mod4  // output a%4
);
    always @(*) begin
        mul2 = /* assignmenmt here */
        div2 = 
        mod2 = 

        mul4 = 
        div4 = 
        mod4 = 
    end
endmodule

lab4/pr_math/wave.vcd
$version Generated by VerilatedVcd $end
$timescale 1ps $end
 $scope module TOP $end
  $var wire 4 # a [3:0] $end
  $var wire 8 $ mul2 [7:0] $end
  $var wire 4 % div2 [3:0] $end
  $var wire 4 & mod2 [3:0] $end
  $var wire 8 ' mul4 [7:0] $end
  $var wire 4 ( div4 [3:0] $end
  $var wire 4 ) mod4 [3:0] $end
  $scope module math $end
   $var wire 4 # a [3:0] $end
   $var wire 8 $ mul2 [7:0] $end
   $var wire 4 % div2 [3:0] $end
   $var wire 4 & mod2 [3:0] $end
   $var wire 8 ' mul4 [7:0] $end
   $var wire 4 ( div4 [3:0] $end
   $var wire 4 ) mod4 [3:0] $end
  $upscope $end
 $upscope $end
$enddefinitions $end


#0
b1011 #
b00010110 $
b0101 %
b0001 &
b00101100 '
b0010 (
b0011 )
#10
b1001 #
b00010010 $
b0100 %
b00100100 '
b0001 )
#20
b0001 #
b00000010 $
b0000 %
b00000100 '
b0000 (
#30
b0110 #
b00001100 $
b0011 %
b0000 &
b00011000 '
b0001 (
b0010 )
#40
b1011 #
b00010110 $
b0101 %
b0001 &
b00101100 '
b0010 (
b0011 )
#50
b0100 #
b00001000 $
b0010 %
b0000 &
b00010000 '
b0001 (
b0000 )
#60
b1110 #
b00011100 $
b0111 %
b00111000 '
b0011 (
b0010 )
#70
b1010 #
b00010100 $
b0101 %
b00101000 '
b0010 (
#80
b1111 #
b00011110 $
b0111 %
b0001 &
b00111100 '
b0011 (
b0011 )
#90
#100
b1101 #
b00011010 $
b0110 %
b00110100 '
b0001 )
#110
b0101 #
b00001010 $
b0010 %
b00010100 '
b0001 (
#120
#130
b1110 #
b00011100 $
b0111 %
b0000 &
b00111000 '
b0011 (
b0010 )
#140
b1000 #
b00010000 $
b0100 %
b00100000 '
b0010 (
b0000 )
#150
b0111 #
b00001110 $
b0011 %
b0001 &
b00011100 '
b0001 (
b0011 )
#160
b0011 #
b00000110 $
b0001 %
b00001100 '
b0000 (
#170
b1000 #
b00010000 $
b0100 %
b0000 &
b00100000 '
b0010 (
b0000 )
#180
b0010 #
b00000100 $
b0001 %
b00001000 '
b0000 (
b0010 )
#190
b0110 #
b00001100 $
b0011 %
b00011000 '
b0001 (
