lab07/ex_bound/design_src/bound.v
module bound (
    input  [7:0] a,
    output reg [7:0] bound_a
);
    always @(*) begin
        bound_a = a > 63 ? 63 : a;
    end
endmodule

lab07/ex_bound/golden/golden_wave.vcd
$version Generated by VerilatedVcd $end
$timescale 1ps $end
 $scope module TOP $end
  $var wire 8 # a [7:0] $end
  $var wire 8 $ bound_a [7:0] $end
  $scope module bound $end
   $var wire 8 % a [7:0] $end
   $var wire 8 & bound_a [7:0] $end
  $upscope $end
 $upscope $end
$enddefinitions $end


#0
b00011000 #
b00011000 $
b00011000 %
b00011000 &
#10
b01101111 #
b00111111 $
b01101111 %
b00111111 &
#20
b01000111 #
b01000111 %
#30
b01011011 #
b01011011 %
#40
b00110000 #
b00110000 $
b00110000 %
b00110000 &
#50
b01001010 #
b00111111 $
b01001010 %
b00111111 &
#60
b00111100 #
b00111100 $
b00111100 %
b00111100 &
#70
b10000101 #
b00111111 $
b10000101 %
b00111111 &
#80
b11111101 #
b11111101 %
#90
b00011111 #
b00011111 $
b00011111 %
b00011111 &
#100
b00000000 #
b00000000 $
b00000000 %
b00000000 &
#110
b00000001 #
b00000001 $
b00000001 %
b00000001 &
#120
b01111111 #
b00111111 $
b01111111 %
b00111111 &
#130
b10000000 #
b10000000 %
#140
b10000001 #
b10000001 %
#150
b10000010 #
b10000010 %
#160
b11111111 #
b11111111 %
#170
b11111010 #
b11111010 %
#180
b11110000 #
b11110000 %
#190
b11001000 #
b11001000 %
