lab06/ex_bigger/design_src/bigger.v
module bigger (
    input [3:0] a, // three random non-negative integer
    input [3:0] b,
    input [3:0] c,
    output reg bgt, // be 1 if a > b
    output reg seq_bgt  // be 1 if a > b > c
);
    always @(*) begin
        bgt      = (a > b);
        seq_bgt  = (a > b) && (b > c); // chained compare
    end
endmodule

lab6/ex_bigger/wave.vcd
$version Generated by VerilatedVcd $end
$timescale 1ps $end
 $scope module TOP $end
  $var wire 4 # a [3:0] $end
  $var wire 4 $ b [3:0] $end
  $var wire 4 % c [3:0] $end
  $var wire 1 & bgt $end
  $var wire 1 ' seq_bgt $end
  $scope module bigger $end
   $var wire 4 # a [3:0] $end
   $var wire 4 $ b [3:0] $end
   $var wire 4 % c [3:0] $end
   $var wire 1 & bgt $end
   $var wire 1 ' seq_bgt $end
  $upscope $end
 $upscope $end
$enddefinitions $end


#0
b1000 #
b1011 $
b0100 %
0&
0'
#10
b0110 #
b0010 $
b1100 %
1&
1'
#20
b1100 #
b0111 $
b0000 %
0&
0'
#30
b0111 #
b0000 $
b1110 %
1&
1'
#40
b0010 #
b1110 $
b0100 %
0'
#50
b1111 #
b1011 $
b0011 %
#60
b0100 #
b0000 $
b1111 %
1'
#70
b1101 #
b1000 $
b0111 %
0'
#80
b1000 #
b1001 $
b1101 %
0&
#90
b1100 #
b0110 $
b0101 %
#100
b0010 #
b0101 $
b1101 %
#110
b0110 #
b0000 $
b1011 %
1&
1'
#120
b0011 #
b1001 $
b1111 %
0'
#130
b1010 #
b0000 $
b0100 %
0&
#140
b1000 #
b1110 $
b0101 %
#150
b1111 #
b1101 $
b0111 %
1&
#160
b1101 #
b1110 $
b1001 %
0&
#170
b0111 #
b1000 $
b1110 %
1&
#180
b0000 #
b0011 $
b0000 %
0&
#190
b0011 #
b1000 $
b1111 %
1&
