lab07/pr_ops/design_src/ops.v
module ops (
    input  [7:0] a,
    input  [7:0] b,
    input  [1:0] op,
    output reg [7:0] o
);

    always @(*) begin
        case (op)
            2'b00: begin // op == 0, o = a + b
                o = //
            end
            2'b01: begin // op == 0, o = a % b
                o =  //
            end
            2'b10: begin // op == 0, o = a & b
                o = //
            end
            2'b11: begin // op == 0, o = a | b
                o = //
            end
            default: o = 8'h00;
        endcase
    end
endmodule

lab07/pr_ops/sim_result/wave.vcd
$version Generated by VerilatedVcd $end
$timescale 1ps $end
 $scope module TOP $end
  $var wire 8 # a [7:0] $end
  $var wire 8 $ b [7:0] $end
  $var wire 2 % op [1:0] $end
  $var wire 8 & o [7:0] $end
  $scope module ops $end
   $var wire 8 ' a [7:0] $end
   $var wire 8 ( b [7:0] $end
   $var wire 2 ) op [1:0] $end
   $var wire 8 * o [7:0] $end
  $upscope $end
 $upscope $end
$enddefinitions $end


#0
b00001010 #
b00000001 $
b00 %
b00001011 &
b00001010 '
b00000001 (
b00 )
b00001011 *
#10
b00000101 #
b00000011 $
b01 %
b00000010 &
b00000101 '
b00000011 (
b01 )
b00000010 *
#20
b00001100 #
b00000111 $
b10 %
b00000100 &
b00001100 '
b00000111 (
b10 )
b00000100 *
#30
b00001000 #
b00000100 $
b11 %
b00001100 &
b00001000 '
b00000100 (
b11 )
b00001100 *
#40
b00000000 #
b00000001 $
b00 %
b00000001 &
b00000000 '
b00000001 (
b00 )
b00000001 *
#50
b00011001 #
b00001010 $
b01 %
b00000101 &
b00011001 '
b00001010 (
b01 )
b00000101 *
#60
b00101000 #
b00001111 $
b10 %
b00001000 &
b00101000 '
b00001111 (
b10 )
b00001000 *
#70
b00010010 #
b00000010 $
b11 %
b00010010 &
b00010010 '
b00000010 (
b11 )
b00010010 *
#80
b00000001 #
b00000001 $
b01 %
b00000000 &
b00000001 '
b00000001 (
b01 )
b00000000 *
#90
b00010100 #
b00000101 $
b00 %
b00011001 &
b00010100 '
b00000101 (
b00 )
b00011001 *
#100
b00100001 #
b00001011 $
b10 %
b00000001 &
b00100001 '
b00001011 (
b10 )
b00000001 *
#110
b01001101 #
b00110111 $
b11 %
b01111111 &
b01001101 '
b00110111 (
b11 )
b01111111 *
#120
b00001110 #
b00000010 $
b00 %
b00010000 &
b00001110 '
b00000010 (
b00 )
b00010000 *
#130
b01100011 #
b00000001 $
b11 %
b01100011 &
b01100011 '
b00000001 (
b11 )
b01100011 *
#140
b00110010 #
b00000011 $
b01 %
b00000010 &
b00110010 '
b00000011 (
b01 )
b00000010 *
#150
b01000010 #
b00010110 $
b10 %
b01000010 '
b00010110 (
b10 )
#160
b01010000 #
b00010000 $
b11 %
b01010000 &
b01010000 '
b00010000 (
b11 )
b01010000 *
#170
b01011000 #
b01100011 $
b00 %
b10111011 &
b01011000 '
b01100011 (
b00 )
b10111011 *
#180
b00101010 #
b00000110 $
b10 %
b00000010 &
b00101010 '
b00000110 (
b10 )
b00000010 *
#190
b00001101 #
b00000111 $
b01 %
b00000110 &
b00001101 '
b00000111 (
b01 )
b00000110 *
