lab10/ex_mod/design_src/mod.v
module mod (
    input clk,
    input rst_n,
    input valid, // indicates the input data is valid at this cycle
    input [7:0] dividend,
    input [7:0] divisor,
    output reg ready, // one cycle pulse to indicate the output data is ready.
    output reg [7:0] remainder
);
    localparam IDLE = 0,
               BUSY = 1,
               OUT  = 2;
    
    reg [1:0] S, S_nxt;
    reg [7:0] a, a_nxt;
    reg [7:0] b, b_nxt;

    always @(*) begin
        case (S)
            IDLE: begin
                if (valid) begin // store the input data, because it is a valid.
                    a_nxt = dividend;
                    b_nxt = divisor;
                    S_nxt = BUSY;
                end
                else begin // hold the current value in registers
                    a_nxt = a;
                    b_nxt = b;
                    S_nxt = IDLE;
                end
            end
            BUSY: begin
                if (a < b) begin // a is the remainder now
                    a_nxt = a;
                    b_nxt = b;
                    S_nxt = OUT;
                end
                else begin // a keep minus b
                    a_nxt = a - b;
                    b_nxt = b;
                    S_nxt = BUSY;
                end
            end
            OUT: begin // go to IDLE directly because this cycle is the ready pulse.
                a_nxt = a;
                b_nxt = b;
                S_nxt = IDLE;
            end
            default: begin
                a_nxt = 0;
                b_nxt = 0;
                S_nxt = IDLE;
            end
        endcase
    end

    always @(posedge clk, negedge rst_n) begin
        if (~rst_n) begin
            S <= IDLE;
            a <= 0;
            b <= 0;
        end
        else begin
            S <= S_nxt;
            a <= a_nxt;
            b <= b_nxt;
        end
    end

    always @(*) begin
        // assign the correct data when the ready pulse is actived
        ready = S == OUT;
        remainder = S == OUT ? a : 0;
    end
endmodule

lab10/ex_mod/wave.vcd
$version Generated by VerilatedVcd $end
$timescale 1ps $end
 $scope module TOP $end
  $var wire 1 & clk $end
  $var wire 1 ' rst_n $end
  $var wire 1 ( valid $end
  $var wire 8 ) dividend [7:0] $end
  $var wire 8 * divisor [7:0] $end
  $var wire 1 + ready $end
  $var wire 8 , remainder [7:0] $end
  $scope module mod $end
   $var wire 1 & clk $end
   $var wire 1 ' rst_n $end
   $var wire 1 ( valid $end
   $var wire 8 ) dividend [7:0] $end
   $var wire 8 * divisor [7:0] $end
   $var wire 1 + ready $end
   $var wire 8 , remainder [7:0] $end
   $var wire 32 0 IDLE [31:0] $end
   $var wire 32 1 BUSY [31:0] $end
   $var wire 32 2 OUT [31:0] $end
   $var wire 2 # S [1:0] $end
   $var wire 2 - S_nxt [1:0] $end
   $var wire 8 $ a [7:0] $end
   $var wire 8 . a_nxt [7:0] $end
   $var wire 8 % b [7:0] $end
   $var wire 8 / b_nxt [7:0] $end
  $upscope $end
 $upscope $end
$enddefinitions $end


#5
b00 #
b00000000 $
b00000000 %
0&
0'
0(
b00000000 )
b00000000 *
0+
b00000000 ,
b00 -
b00000000 .
b00000000 /
b00000000000000000000000000000000 0
b00000000000000000000000000000001 1
b00000000000000000000000000000010 2
#10
#15
#20
1&
#25
0&
#30
1&
#35
0&
1'
#40
1&
#45
0&
1(
b00001000 )
b00000010 *
b01 -
b00001000 .
b00000010 /
#50
b01 #
b00001000 $
b00000010 %
1&
b00000110 .
#55
0&
0(
b00000000 )
b00000000 *
#60
b00000110 $
1&
b00000100 .
#65
0&
#70
b00000100 $
1&
b00000010 .
#75
0&
#80
b00000010 $
1&
b00000000 .
#85
0&
#90
b00000000 $
1&
b10 -
#95
0&
#100
b10 #
1&
1+
b00 -
#105
0&
#110
b00 #
1&
0+
#115
0&
#120
1&
#125
0&
#130
1&
#135
0&
#140
1&
#145
0&
#150
1&
#155
0&
#160
1&
#165
0&
#170
1&
#175
0&
#180
1&
#185
0&
#190
1&
#195
0&
#200
1&
#205
b00000000 %
0&
0'
#215
#225
#235
#245
#250
1'
1(
b00010011 )
b00000011 *
b01 -
b00010011 .
b00000011 /
#255
b01 #
b00010011 $
b00000011 %
1&
b00010000 .
#260
0&
0(
b00000000 )
b00000000 *
#265
b00010000 $
1&
b00001101 .
#270
0&
#275
b00001101 $
1&
b00001010 .
#280
0&
#285
b00001010 $
1&
b00000111 .
#290
0&
#295
b00000111 $
1&
b00000100 .
#300
0&
#305
b00000100 $
1&
b00000001 .
#310
0&
#315
b00000001 $
1&
b10 -
#320
0&
#325
b10 #
1&
1+
b00000001 ,
b00 -
#330
0&
#335
b00 #
1&
0+
b00000000 ,
#340
0&
#345
1&
#350
0&
#355
1&
#360
0&
#365
1&
#370
0&
#375
1&
#380
0&
#385
1&
#390
0&
#395
1&
#400
0&
#405
1&
#410
0&
#415
1&
#420
0&
#425
1&
#430
b00000000 $
b00000000 %
0&
0'
#440
#450
#460
#470
#475
1'
1(
b00000010 )
b00000101 *
b01 -
b00000010 .
b00000101 /
#480
b01 #
b00000010 $
b00000101 %
1&
b10 -
#485
0&
0(
b00000000 )
b00000000 *
#490
b10 #
1&
1+
b00000010 ,
b00 -
#495
0&
#500
b00 #
1&
0+
b00000000 ,
#505
0&
#510
1&
#515
0&
#520
1&
#525
0&
#530
1&
#535
0&
#540
1&
#545
0&
#550
1&
#555
0&
#560
1&
#565
0&
#570
1&
#575
0&
#580
1&
#585
0&
#590
1&
#595
b00000000 $
b00000000 %
0&
0'
#605
#615
#625
#635
#640
1'
1(
b01001101 )
b00001000 *
b01 -
b01001101 .
b00001000 /
#645
b01 #
b01001101 $
b00001000 %
1&
b01000101 .
#650
0&
0(
b00000000 )
b00000000 *
#655
b01000101 $
1&
b00111101 .
#660
0&
#665
b00111101 $
1&
b00110101 .
#670
0&
#675
b00110101 $
1&
b00101101 .
#680
0&
#685
b00101101 $
1&
b00100101 .
#690
0&
#695
b00100101 $
1&
b00011101 .
#700
0&
#705
b00011101 $
1&
b00010101 .
#710
0&
#715
b00010101 $
1&
b00001101 .
#720
0&
#725
b00001101 $
1&
b00000101 .
#730
0&
#735
b00000101 $
1&
b10 -
#740
0&
#745
b10 #
1&
1+
b00000101 ,
b00 -
#750
0&
#755
b00 #
1&
0+
b00000000 ,
#760
0&
#765
1&
#770
0&
#775
1&
#780
0&
#785
1&
#790
0&
#795
1&
#800
0&
#805
1&
#810
0&
#815
1&
#820
0&
#825
1&
#830
0&
#835
1&
#840
0&
#845
1&
#850
b00000000 $
b00000000 %
0&
0'
#860
#870
#880
#890
#895
1'
1(
b01111111 )
b00000001 *
b01 -
b01111111 .
b00000001 /
#900
b01 #
b01111111 $
b00000001 %
1&
b01111110 .
#905
0&
0(
b00000000 )
b00000000 *
#910
b01111110 $
1&
b01111101 .
#915
0&
#920
b01111101 $
1&
b01111100 .
#925
0&
#930
b01111100 $
1&
b01111011 .
#935
0&
#940
b01111011 $
1&
b01111010 .
#945
0&
#950
b01111010 $
1&
b01111001 .
#955
0&
#960
b01111001 $
1&
b01111000 .
#965
0&
#970
b01111000 $
1&
b01110111 .
#975
0&
#980
b01110111 $
1&
b01110110 .
#985
0&
#990
b01110110 $
1&
b01110101 .
#995
0&
#1000
b01110101 $
1&
b01110100 .
#1005
0&
#1010
b01110100 $
1&
b01110011 .
#1015
0&
#1020
b01110011 $
1&
b01110010 .
#1025
0&
#1030
b01110010 $
1&
b01110001 .
#1035
0&
#1040
b01110001 $
1&
b01110000 .
#1045
0&
#1050
b01110000 $
1&
b01101111 .
#1055
0&
#1060
b01101111 $
1&
b01101110 .
#1065
0&
#1070
b01101110 $
1&
b01101101 .
#1075
0&
#1080
b01101101 $
1&
b01101100 .
#1085
0&
#1090
b01101100 $
1&
b01101011 .
#1095
0&
#1100
b01101011 $
1&
b01101010 .
#1105
0&
#1110
b01101010 $
1&
b01101001 .
#1115
0&
#1120
b01101001 $
1&
b01101000 .
#1125
0&
#1130
b01101000 $
1&
b01100111 .
#1135
0&
#1140
b01100111 $
1&
b01100110 .
#1145
0&
#1150
b01100110 $
1&
b01100101 .
#1155
0&
#1160
b01100101 $
1&
b01100100 .
#1165
0&
#1170
b01100100 $
1&
b01100011 .
#1175
0&
#1180
b01100011 $
1&
b01100010 .
#1185
0&
#1190
b01100010 $
1&
b01100001 .
#1195
0&
#1200
b01100001 $
1&
b01100000 .
#1205
0&
#1210
b01100000 $
1&
b01011111 .
#1215
0&
#1220
b01011111 $
1&
b01011110 .
#1225
0&
#1230
b01011110 $
1&
b01011101 .
#1235
0&
#1240
b01011101 $
1&
b01011100 .
#1245
0&
#1250
b01011100 $
1&
b01011011 .
#1255
0&
#1260
b01011011 $
1&
b01011010 .
#1265
0&
#1270
b01011010 $
1&
b01011001 .
#1275
0&
#1280
b01011001 $
1&
b01011000 .
#1285
0&
#1290
b01011000 $
1&
b01010111 .
#1295
0&
#1300
b01010111 $
1&
b01010110 .
#1305
0&
#1310
b01010110 $
1&
b01010101 .
#1315
0&
#1320
b01010101 $
1&
b01010100 .
#1325
0&
#1330
b01010100 $
1&
b01010011 .
#1335
0&
#1340
b01010011 $
1&
b01010010 .
#1345
0&
#1350
b01010010 $
1&
b01010001 .
#1355
0&
#1360
b01010001 $
1&
b01010000 .
#1365
0&
#1370
b01010000 $
1&
b01001111 .
#1375
0&
#1380
b01001111 $
1&
b01001110 .
#1385
0&
#1390
b01001110 $
1&
b01001101 .
#1395
0&
#1400
b01001101 $
1&
b01001100 .
#1405
0&
#1410
b01001100 $
1&
b01001011 .
#1415
0&
#1420
b01001011 $
1&
b01001010 .
#1425
0&
#1430
b01001010 $
1&
b01001001 .
#1435
0&
#1440
b01001001 $
1&
b01001000 .
#1445
0&
#1450
b01001000 $
1&
b01000111 .
#1455
0&
#1460
b01000111 $
1&
b01000110 .
#1465
0&
#1470
b01000110 $
1&
b01000101 .
#1475
0&
#1480
b01000101 $
1&
b01000100 .
#1485
0&
#1490
b01000100 $
1&
b01000011 .
#1495
0&
#1500
b01000011 $
1&
b01000010 .
#1505
0&
#1510
b01000010 $
1&
b01000001 .
#1515
0&
#1520
b01000001 $
1&
b01000000 .
#1525
0&
#1530
b01000000 $
1&
b00111111 .
#1535
0&
#1540
b00111111 $
1&
b00111110 .
#1545
0&
#1550
b00111110 $
1&
b00111101 .
#1555
0&
#1560
b00111101 $
1&
b00111100 .
#1565
0&
#1570
b00111100 $
1&
b00111011 .
#1575
0&
#1580
b00111011 $
1&
b00111010 .
#1585
0&
#1590
b00111010 $
1&
b00111001 .
#1595
0&
#1600
b00111001 $
1&
b00111000 .
#1605
0&
#1610
b00111000 $
1&
b00110111 .
#1615
0&
#1620
b00110111 $
1&
b00110110 .
#1625
0&
#1630
b00110110 $
1&
b00110101 .
#1635
0&
#1640
b00110101 $
1&
b00110100 .
#1645
0&
#1650
b00110100 $
1&
b00110011 .
#1655
0&
#1660
b00110011 $
1&
b00110010 .
#1665
0&
#1670
b00110010 $
1&
b00110001 .
#1675
0&
#1680
b00110001 $
1&
b00110000 .
#1685
0&
#1690
b00110000 $
1&
b00101111 .
#1695
0&
#1700
b00101111 $
1&
b00101110 .
#1705
0&
#1710
b00101110 $
1&
b00101101 .
#1715
0&
#1720
b00101101 $
1&
b00101100 .
#1725
0&
#1730
b00101100 $
1&
b00101011 .
#1735
0&
#1740
b00101011 $
1&
b00101010 .
#1745
0&
#1750
b00101010 $
1&
b00101001 .
#1755
0&
#1760
b00101001 $
1&
b00101000 .
#1765
0&
#1770
b00101000 $
1&
b00100111 .
#1775
0&
#1780
b00100111 $
1&
b00100110 .
#1785
0&
#1790
b00100110 $
1&
b00100101 .
#1795
0&
#1800
b00100101 $
1&
b00100100 .
#1805
0&
#1810
b00100100 $
1&
b00100011 .
#1815
0&
#1820
b00100011 $
1&
b00100010 .
#1825
0&
#1830
b00100010 $
1&
b00100001 .
#1835
0&
#1840
b00100001 $
1&
b00100000 .
#1845
0&
#1850
b00100000 $
1&
b00011111 .
#1855
0&
#1860
b00011111 $
1&
b00011110 .
#1865
0&
#1870
b00011110 $
1&
b00011101 .
#1875
0&
#1880
b00011101 $
1&
b00011100 .
#1885
0&
#1890
b00011100 $
1&
b00011011 .
#1895
b00 #
b00000000 $
b00000000 %
0&
0'
#1905
#1915
#1925
#1935
#1940
1'
1(
b00001001 *
b00000000 .
b00001001 /
#1945
b01 #
b00001001 %
1&
b10 -
#1950
0&
0(
b00000000 *
#1955
b10 #
1&
1+
b00 -
#1960
0&
#1965
b00 #
1&
0+
#1970
0&
#1975
1&
#1980
0&
#1985
1&
#1990
0&
#1995
1&
#2000
0&
#2005
1&
#2010
0&
#2015
1&
#2020
0&
#2025
1&
#2030
0&
#2035
1&
#2040
0&
#2045
1&
#2050
0&
#2055
1&
#2060
b00000000 %
0&
0'
