lab05/pr_mul/design_src/mul.v
module mul (
    input  [3:0] a,
    output reg [7:0] mul2, // = a << 1
    output reg [7:0] mul4, // = a << 2
    output reg [7:0] mul8, // = a << 3
    output reg       be4   // = if a%4 is 0. 1 for yes, 0 for no.
);
    always @(*) begin
        mul2 = 
        mul4 = 
        mul8 = 
        be4  = // hint: when a%4 is zero, the first 2 bits from the right end of a should both be '0';
    end
endmodule

lab5/pr_mul/wave.vcd
$version Generated by VerilatedVcd $end
$timescale 1ps $end
 $scope module TOP $end
  $var wire 4 # a [3:0] $end
  $var wire 8 $ mul2 [7:0] $end
  $var wire 8 % mul4 [7:0] $end
  $var wire 8 & mul8 [7:0] $end
  $var wire 1 ' be4 $end
  $scope module mul $end
   $var wire 4 # a [3:0] $end
   $var wire 8 $ mul2 [7:0] $end
   $var wire 8 % mul4 [7:0] $end
   $var wire 8 & mul8 [7:0] $end
   $var wire 1 ' be4 $end
  $upscope $end
 $upscope $end
$enddefinitions $end


#0
b1101 #
b00011010 $
b00110100 %
b01101000 &
0'
#10
b1001 #
b00010010 $
b00100100 %
b01001000 &
#20
b0101 #
b00001010 $
b00010100 %
b00101000 &
#30
b1011 #
b00010110 $
b00101100 %
b01011000 &
#40
b0100 #
b00001000 $
b00010000 %
b00100000 &
1'
#50
b1110 #
b00011100 $
b00111000 %
b01110000 &
0'
#60
b0101 #
b00001010 $
b00010100 %
b00101000 &
#70
b1110 #
b00011100 $
b00111000 %
b01110000 &
#80
b1000 #
b00010000 $
b00100000 %
b01000000 &
1'
#90
b1111 #
b00011110 $
b00111100 %
b01111000 &
0'
#100
b0110 #
b00001100 $
b00011000 %
b00110000 &
#110
b0100 #
b00001000 $
b00010000 %
b00100000 &
1'
#120
b0110 #
b00001100 $
b00011000 %
b00110000 &
0'
#130
b1110 #
b00011100 $
b00111000 %
b01110000 &
#140
b1101 #
b00011010 $
b00110100 %
b01101000 &
#150
#160
b0111 #
b00001110 $
b00011100 %
b00111000 &
#170
b1011 #
b00010110 $
b00101100 %
b01011000 &
#180
b1101 #
b00011010 $
b00110100 %
b01101000 &
#190
b0100 #
b00001000 $
b00010000 %
b00100000 &
1'
